wgrp/__init__.py
wgrp/base_functions.py
wgrp/compute.py
wgrp/getcomputer.py
wgrp/mle_wgrp.py
wgrp/model.py
wgrp/moments.py
wgrp/r_functions.py
wgrp/virtual_ages.py
wgrp/wgrp_functions.py
wgrp-0.1.3.dist-info/LICENSE
wgrp-0.1.3.dist-info/METADATA
wgrp-0.1.3.dist-info/WHEEL
wgrp-0.1.3.dist-info/RECORD
