Metadata-Version: 2.3
Name: wgrp
Version: 0.1.3
Summary: A data science package for analyzing generalized renewal processes. The wgrp package is a powerful data science tool designed for analyzing generalized renewal processes, with a special focus on Weibull-based renewal processes (WGRP).
License: APACHE 2.0
Author: Junior Dantas
Author-email: juniordante01@gmail.com
Requires-Python: >=3.11,<4.0
Classifier: Development Status :: 5 - Production/Stable
Classifier: Intended Audience :: Developers
Classifier: Intended Audience :: Science/Research
Classifier: License :: Other/Proprietary License
Classifier: Operating System :: OS Independent
Classifier: Programming Language :: Python :: 3
Classifier: Programming Language :: Python :: 3.11
Classifier: Programming Language :: Python :: 3.12
Classifier: Programming Language :: Python :: 3.13
Classifier: Topic :: Scientific/Engineering
Classifier: Topic :: Software Development
Requires-Dist: matplotlib (>=3.4.0)
Requires-Dist: numpy (>=1.21.0)
Requires-Dist: pandas (>=1.3.0)
Requires-Dist: pyswarm (>=0.5)
Requires-Dist: scipy (>=1.9.0)
